dpla/__init__.py
dpla/api.py
dpla/settings.py
dpla-0.5.dist-info/METADATA
dpla-0.5.dist-info/WHEEL
dpla-0.5.dist-info/top_level.txt
dpla-0.5.dist-info/RECORD
