Metadata-Version: 2.1
Name: dpla
Version: 0.5
Summary: A client for the Digital Public Library of America (DPLA) API
Home-page: https://github.com/bibliotechy/DPyLA
Download-URL: https://github.com/bibliotechy/DPyLA/releases/latest
Author: Chad Nelson
Author-email: Chad Nelson <chadbnelson@gmail.com>
Project-URL: Homepage, https://github.com/bibliotechy/dpyla
Project-URL: Bug Tracker, https://github.com/bibliotechy/dpyla/issues
Keywords: libraries,DPLA,museums
Classifier: Programming Language :: Python :: 3
Classifier: Development Status :: 5 - Production/Stable
Classifier: Operating System :: OS Independent
Requires-Python: >=3.7
Requires-Dist: requests
